[
  {
    "name": "Aarambha Chautari Laghubitta Bittiya Sanstha Limited",
    "code": "ACLBSL",
    "ltp": "1,076.00",
    "change_%": "-2.62",
    "open": "1,070.00",
    "high": "1,090.00",
    "low": "1,085.00",
    "qty": "2,182"
  },
  {
    "name": "Agriculture Development Bank Limited",
    "code": "ADBL",
    "ltp": "287.50",
    "change_%": "0.07",
    "open": "285.00",
    "high": "290.00",
    "low": "290.00",
    "qty": "8,492"
  },
  {
    "name": "Asian Hydropower Limited",
    "code": "AHL",
    "ltp": "732.00",
    "change_%": "-0.83",
    "open": "720.00",
    "high": "742.90",
    "low": "740.00",
    "qty": "2,334"
  },
  {
    "name": "Arun Valley Hydropower Development Co. Ltd.",
    "code": "AHPC",
    "ltp": "254.00",
    "change_%": "-1.57",
    "open": "250.00",
    "high": "263.00",
    "low": "259.90",
    "qty": "67,853"
  },
  {
    "name": "Ankhu Khola Jalvidhyut Company Ltd",
    "code": "AKJCL",
    "ltp": "205.00",
    "change_%": "-0.98",
    "open": "203.10",
    "high": "210.00",
    "low": "209.00",
    "qty": "74,812"
  },
  {
    "name": "Arun Kabeli Power Ltd.",
    "code": "AKPL",
    "ltp": "228.00",
    "change_%": "-2.14",
    "open": "226.00",
    "high": "235.00",
    "low": "233.10",
    "qty": "86,404"
  },
  {
    "name": "Asha Laghubitta Bittiya Sanstha Limited",
    "code": "ALBSL",
    "ltp": "834.90",
    "change_%": "-2.19",
    "open": "828.50",
    "high": "842.00",
    "low": "841.00",
    "qty": "1,706"
  },
  {
    "name": "Asian Life Insurance Co. Limited",
    "code": "ALICL",
    "ltp": "765.00",
    "change_%": "-0.6",
    "open": "752.30",
    "high": "774.00",
    "low": "770.00",
    "qty": "35,734"
  },
  {
    "name": "Aatmanirbhar Laghubitta Bittiya Sanstha Limited",
    "code": "ANLB",
    "ltp": "5,050.00",
    "change_%": "-0.3",
    "open": "5,011.00",
    "high": "5,109.00",
    "low": "5,011.00",
    "qty": "160"
  },
  {
    "name": "Api Power Company Ltd.",
    "code": "API",
    "ltp": "271.80",
    "change_%": "-1.17",
    "open": "270.20",
    "high": "280.00",
    "low": "280.00",
    "qty": "73,530"
  },
  {
    "name": "Aviyan Laghubitta Bittiya Sanstha Limited",
    "code": "AVYAN",
    "ltp": "1,066.00",
    "change_%": "-2.18",
    "open": "1,052.10",
    "high": "1,086.30",
    "low": "1,069.00",
    "qty": "5,836"
  },
  {
    "name": "Barun Hydropower Co. Ltd.",
    "code": "BARUN",
    "ltp": "505.00",
    "change_%": "-2.42",
    "open": "504.90",
    "high": "520.00",
    "low": "516.00",
    "qty": "74,536"
  },
  {
    "name": "Bishal Bazar Company Limited",
    "code": "BBC",
    "ltp": "5,701.00",
    "change_%": "1.88",
    "open": "5,486.00",
    "high": "5,750.00",
    "low": "5,501.00",
    "qty": "2,159"
  },
  {
    "name": " Bhugol Energy Development Company Limited ",
    "code": "BEDC",
    "ltp": "793.00",
    "change_%": "-0.96",
    "open": "783.00",
    "high": "816.70",
    "low": "816.70",
    "qty": "14,079"
  },
  {
    "name": "Best Finance Company Ltd.",
    "code": "BFC",
    "ltp": "567.00",
    "change_%": "-0.04",
    "open": "555.40",
    "high": "578.00",
    "low": "577.00",
    "qty": "14,736"
  },
  {
    "name": "Bhagawati Hydropower Development Company Ltd.",
    "code": "BGWT",
    "ltp": "1,021.00",
    "change_%": "-1.35",
    "open": "1,008.00",
    "high": "1,060.00",
    "low": "1,016.00",
    "qty": "1,557"
  },
  {
    "name": "Bindyabasini Hydropower Development Company Limited",
    "code": "BHDC",
    "ltp": "595.00",
    "change_%": "-1.11",
    "open": "581.30",
    "high": "616.00",
    "low": "613.00",
    "qty": "6,276"
  },
  {
    "name": "Balephi Hydropower Limited",
    "code": "BHL",
    "ltp": "335.30",
    "change_%": "-1.11",
    "open": "333.20",
    "high": "340.00",
    "low": "340.00",
    "qty": "2,970"
  },
  {
    "name": "Barahi Hydropower Public Limited",
    "code": "BHPL",
    "ltp": "1,042.00",
    "change_%": "0.84",
    "open": "1,012.70",
    "high": "1,047.00",
    "low": "1,012.70",
    "qty": "1,013"
  },
  {
    "name": "Buddhabhumi Nepal Hydropower Company Limited",
    "code": "BNHC",
    "ltp": "515.00",
    "change_%": "-0.34",
    "open": "509.10",
    "high": "517.00",
    "low": "516.00",
    "qty": "8,314"
  },
  {
    "name": "Bottlers Nepal (Terai",
    "code": "BNT",
    "ltp": "13,277.00",
    "change_%": "0.68",
    "open": "13,100.00",
    "high": "13,277.00",
    "low": "13,188.00",
    "qty": "60"
  },
  {
    "name": "Butwal Power Company Limited",
    "code": "BPCL",
    "ltp": "399.00",
    "change_%": "-0.28",
    "open": "393.00",
    "high": "400.10",
    "low": "398.00",
    "qty": "1,980"
  },
  {
    "name": "Citizens Super 30 Mutual Fund",
    "code": "C30MF",
    "ltp": "8.92",
    "change_%": "-1",
    "open": "8.85",
    "high": "8.92",
    "low": "8.90",
    "qty": "900"
  },
  {
    "name": "Chhimek Laghubitta Bittiya Sanstha Limited",
    "code": "CBBL",
    "ltp": "856.00",
    "change_%": "0.3",
    "open": "849.00",
    "high": "856.00",
    "low": "854.50",
    "qty": "9,670"
  },
  {
    "name": "Civil Bank Debenture 2088",
    "code": "CBLD88",
    "ltp": "1,131.00",
    "change_%": "0.53",
    "open": "1,131.00",
    "high": "1,131.00",
    "low": "1,131.00",
    "qty": "25"
  },
  {
    "name": "Central Finance Co. Ltd.",
    "code": "CFCL",
    "ltp": "560.00",
    "change_%": "-1.31",
    "open": "551.00",
    "high": "590.00",
    "low": "567.40",
    "qty": "22,835"
  },
  {
    "name": "Chandragiri Hills Limited",
    "code": "CGH",
    "ltp": "867.00",
    "change_%": "-1.47",
    "open": "860.00",
    "high": "880.00",
    "low": "879.00",
    "qty": "17,438"
  },
  {
    "name": "Chilime Hydropower Company Limited",
    "code": "CHCL",
    "ltp": "484.00",
    "change_%": "-1.29",
    "open": "481.00",
    "high": "491.00",
    "low": "490.00",
    "qty": "28,918"
  },
  {
    "name": "CEDB Holdings Limited",
    "code": "CHDC",
    "ltp": "2,355.00",
    "change_%": "0.97",
    "open": "2,306.00",
    "high": "2,385.00",
    "low": "2,338.00",
    "qty": "90,850"
  },
  {
    "name": "Chhyangdi Hydropower Ltd.",
    "code": "CHL",
    "ltp": "495.00",
    "change_%": "-3.3",
    "open": "486.00",
    "high": "514.90",
    "low": "505.30",
    "qty": "152,778"
  },
  {
    "name": "Citizen Investment Trust",
    "code": "CIT",
    "ltp": "1,985.00",
    "change_%": "-0.11",
    "open": "1,970.00",
    "high": "1,999.00",
    "low": "1,988.00",
    "qty": "3,806"
  },
  {
    "name": "City Hotel Limited",
    "code": "CITY",
    "ltp": "855.30",
    "change_%": "-2.2",
    "open": "850.20",
    "high": "877.00",
    "low": "860.20",
    "qty": "2,980"
  },
  {
    "name": "10% Citizens Bank Debenture 2090",
    "code": "CIZBD90",
    "ltp": "1,120.10",
    "change_%": "0.01",
    "open": "1,120.10",
    "high": "1,120.10",
    "low": "1,120.10",
    "qty": "25"
  },
  {
    "name": "Chirkhwa Hydropower Limited",
    "code": "CKHL",
    "ltp": "722.20",
    "change_%": "-1.08",
    "open": "707.10",
    "high": "731.00",
    "low": "720.00",
    "qty": "1,560"
  },
  {
    "name": "Citizen Life Insurance Company Limited",
    "code": "CLI",
    "ltp": "510.00",
    "change_%": "-1.27",
    "open": "510.00",
    "high": "521.00",
    "low": "516.00",
    "qty": "16,778"
  },
  {
    "name": "CITIZENS MUTUAL FUND 2",
    "code": "CMF2",
    "ltp": "9.35",
    "change_%": "0.97",
    "open": "9.26",
    "high": "9.35",
    "low": "9.26",
    "qty": "5,500"
  },
  {
    "name": "Corporate Development Bank Limited",
    "code": "CORBL",
    "ltp": "1,844.90",
    "change_%": "3.27",
    "open": "1,750.00",
    "high": "1,858.40",
    "low": "1,822.00",
    "qty": "9,192"
  },
  {
    "name": "CYC Nepal Laghubitta Bittiya Sanstha Limited",
    "code": "CYCL",
    "ltp": "1,630.00",
    "change_%": "-0.13",
    "open": "1,591.00",
    "high": "1,636.00",
    "low": "1,610.00",
    "qty": "2,624"
  },
  {
    "name": "Citizen Bank International Limited",
    "code": "CZBIL",
    "ltp": "213.00",
    "change_%": "0.5",
    "open": "210.30",
    "high": "214.00",
    "low": "211.10",
    "qty": "27,780"
  },
  {
    "name": "Deprosc Laghubitta Bittiya Sanstha Limited",
    "code": "DDBL",
    "ltp": "786.50",
    "change_%": "0.12",
    "open": "778.00",
    "high": "788.00",
    "low": "780.00",
    "qty": "3,707"
  },
  {
    "name": "Dibyashwori Hydropower Ltd.",
    "code": "DHPL",
    "ltp": "399.00",
    "change_%": "-0.51",
    "open": "392.10",
    "high": "408.00",
    "low": "394.00",
    "qty": "57,726"
  },
  {
    "name": "Dhaulagiri Laghubitta Bittiya Sanstha Limited",
    "code": "DLBS",
    "ltp": "1,575.00",
    "change_%": "-1.36",
    "open": "1,541.00",
    "high": "1,618.00",
    "low": "1,591.00",
    "qty": "1,398"
  },
  {
    "name": "Dolti Power Company Limited",
    "code": "DOLTI",
    "ltp": "694.00",
    "change_%": "0.31",
    "open": "681.00",
    "high": "703.00",
    "low": "681.00",
    "qty": "14,131"
  },
  {
    "name": "Dordi Khola Jal Bidyut Company Limited",
    "code": "DORDI",
    "ltp": "385.00",
    "change_%": "-2.41",
    "open": "383.20",
    "high": "402.40",
    "low": "402.40",
    "qty": "15,748"
  },
  {
    "name": "Everest Bank Limited",
    "code": "EBL",
    "ltp": "601.20",
    "change_%": "-0.95",
    "open": "600.00",
    "high": "609.80",
    "low": "609.80",
    "qty": "18,969"
  },
  {
    "name": "8.5% of Everest Bank Limited Debenture 2086",
    "code": "EBLD86",
    "ltp": "1,044.00",
    "change_%": "0.1",
    "open": "1,044.00",
    "high": "1,044.00",
    "low": "1,044.00",
    "qty": "25"
  },
  {
    "name": "Everest Bank Limited Energy Bond, 2089",
    "code": "EBLEB89",
    "ltp": "1,010.00",
    "change_%": "0",
    "open": "1,000.00",
    "high": "1,010.00",
    "low": "1,000.00",
    "qty": "150"
  },
  {
    "name": "Excel Development Bank Ltd.",
    "code": "EDBL",
    "ltp": "643.00",
    "change_%": "-0.59",
    "open": "633.00",
    "high": "659.70",
    "low": "635.00",
    "qty": "20,833"
  },
  {
    "name": "Eastern Hydropower Limited",
    "code": "EHPL",
    "ltp": "690.00",
    "change_%": "-1.43",
    "open": "677.00",
    "high": "712.00",
    "low": "712.00",
    "qty": "3,703"
  },
  {
    "name": "Emerging Nepal Limited",
    "code": "ENL",
    "ltp": "1,183.20",
    "change_%": "0.5",
    "open": "1,154.00",
    "high": "1,225.00",
    "low": "1,178.00",
    "qty": "3,782"
  },
  {
    "name": "First Micro Finance Laghubitta Bittiya Sanstha Limited",
    "code": "FMDBL",
    "ltp": "780.00",
    "change_%": "0.15",
    "open": "765.00",
    "high": "799.00",
    "low": "790.00",
    "qty": "22,007"
  },
  {
    "name": "Forward Microfinance Laghubitta Bittiya Sanstha Ltd.",
    "code": "FOWAD",
    "ltp": "1,185.00",
    "change_%": "-1.33",
    "open": "1,177.10",
    "high": "1,190.00",
    "low": "1,182.00",
    "qty": "888"
  },
  {
    "name": "Garima Debenture, 2085",
    "code": "GBBD85",
    "ltp": "1,037.10",
    "change_%": "0.14",
    "open": "1,037.10",
    "high": "1,037.10",
    "low": "1,037.10",
    "qty": "25"
  },
  {
    "name": "Garima Bikas Bank Limited",
    "code": "GBBL",
    "ltp": "394.00",
    "change_%": "-0.52",
    "open": "391.10",
    "high": "396.00",
    "low": "396.00",
    "qty": "16,618"
  },
  {
    "name": "Global IME Bank Debenture 2084/85",
    "code": "GBILD84/85",
    "ltp": "1,190.00",
    "change_%": "-1.24",
    "open": "1,190.00",
    "high": "1,190.00",
    "low": "1,190.00",
    "qty": "50"
  },
  {
    "name": "Global IME Bank Limited",
    "code": "GBIME",
    "ltp": "217.50",
    "change_%": "-0.92",
    "open": "217.20",
    "high": "221.50",
    "low": "220.00",
    "qty": "67,219"
  },
  {
    "name": "Grameen Bikas Laghubitta Bittiya Sanstha Ltd.",
    "code": "GBLBS",
    "ltp": "838.00",
    "change_%": "-0.18",
    "open": "820.00",
    "high": "841.10",
    "low": "841.10",
    "qty": "7,846"
  },
  {
    "name": "Ghorahi Cement Industry Limited",
    "code": "GCIL",
    "ltp": "547.00",
    "change_%": "-2.79",
    "open": "543.00",
    "high": "573.00",
    "low": "551.50",
    "qty": "110,406"
  },
  {
    "name": "Goodwill Finance Co. Ltd.",
    "code": "GFCL",
    "ltp": "668.00",
    "change_%": "-1.02",
    "open": "662.00",
    "high": "675.00",
    "low": "675.00",
    "qty": "8,971"
  },
  {
    "name": "Ghalemdi Hydro Limited",
    "code": "GHL",
    "ltp": "279.80",
    "change_%": "-2.39",
    "open": "276.00",
    "high": "291.00",
    "low": "286.00",
    "qty": "274,368"
  },
  {
    "name": "Global IME Balanced Fund-1",
    "code": "GIBF1",
    "ltp": "9.81",
    "change_%": "-0.41",
    "open": "9.66",
    "high": "9.85",
    "low": "9.66",
    "qty": "1,100"
  },
  {
    "name": "Global IME Laghubitta Bittiya Sanstha Ltd.",
    "code": "GILB",
    "ltp": "1,279.80",
    "change_%": "0.34",
    "open": "1,255.00",
    "high": "1,279.80",
    "low": "1,275.50",
    "qty": "285"
  },
  {
    "name": "Gurans Laghubitta Bittiya Sanstha Limited",
    "code": "GLBSL",
    "ltp": "2,987.00",
    "change_%": "-4.48",
    "open": "2,911.00",
    "high": "3,064.70",
    "low": "3,064.70",
    "qty": "3,979"
  },
  {
    "name": "Greenlife Hydropower Limited",
    "code": "GLH",
    "ltp": "244.00",
    "change_%": "-1.34",
    "open": "242.00",
    "high": "249.90",
    "low": "244.00",
    "qty": "25,756"
  },
  {
    "name": "Ganapati Microfinance Bittiya Sanstha Ltd",
    "code": "GMFBS",
    "ltp": "1,649.90",
    "change_%": "-1.51",
    "open": "1,620.20",
    "high": "1,675.00",
    "low": "1,652.00",
    "qty": "1,519"
  },
  {
    "name": "Guheshowori Merchant Bank & Finance Co. Ltd.",
    "code": "GMFIL",
    "ltp": "514.90",
    "change_%": "-0.29",
    "open": "507.00",
    "high": "524.80",
    "low": "520.00",
    "qty": "10,049"
  },
  {
    "name": "Guardian Micro-Life Insurance Limited",
    "code": "GMLI",
    "ltp": "2,579.80",
    "change_%": "10",
    "open": "2,345.00",
    "high": "2,579.80",
    "low": "2,345.00",
    "qty": "73,884"
  },
  {
    "name": "Green Development Bank Ltd.",
    "code": "GRDBL",
    "ltp": "1,336.00",
    "change_%": "0.01",
    "open": "1,309.20",
    "high": "1,389.00",
    "low": "1,309.20",
    "qty": "8,997"
  },
  {
    "name": "Garima Samriddhi Yojana",
    "code": "GSY",
    "ltp": "8.95",
    "change_%": "-0.67",
    "open": "8.85",
    "high": "9.07",
    "low": "8.85",
    "qty": "3,250"
  },
  {
    "name": "Gurkhas Finance Ltd.",
    "code": "GUFL",
    "ltp": "596.80",
    "change_%": "-0.34",
    "open": "587.00",
    "high": "609.80",
    "low": "609.80",
    "qty": "8,386"
  },
  {
    "name": "Green Ventures Limited",
    "code": "GVL",
    "ltp": "461.00",
    "change_%": "-2.28",
    "open": "459.40",
    "high": "471.00",
    "low": "471.00",
    "qty": "8,261"
  },
  {
    "name": "12% Goodwill finance Debenture 2083",
    "code": "GWFD83",
    "ltp": "1,180.00",
    "change_%": "-0.96",
    "open": "1,180.00",
    "high": "1,180.00",
    "low": "1,180.00",
    "qty": "15"
  },
  {
    "name": "Himalayan 80-20",
    "code": "H8020",
    "ltp": "10.30",
    "change_%": "-2",
    "open": "10.20",
    "high": "10.30",
    "low": "10.30",
    "qty": "10,800"
  },
  {
    "name": "Hathway Investment Nepal Limited",
    "code": "HATHY",
    "ltp": "1,311.00",
    "change_%": "-0.92",
    "open": "1,276.00",
    "high": "1,334.00",
    "low": "1,323.11",
    "qty": "40,635"
  },
  {
    "name": "Himalayan Bank Limited",
    "code": "HBL",
    "ltp": "237.50",
    "change_%": "-0.2",
    "open": "231.60",
    "high": "239.00",
    "low": "235.00",
    "qty": "31,846"
  },
  {
    "name": "Himal Dolakha Hydropower Company Limited",
    "code": "HDHPC",
    "ltp": "200.00",
    "change_%": "-0.95",
    "open": "199.00",
    "high": "205.90",
    "low": "205.90",
    "qty": "70,287"
  },
  {
    "name": "Himalayan Distillery Limited",
    "code": "HDL",
    "ltp": "1,200.20",
    "change_%": "-0.98",
    "open": "1,195.00",
    "high": "1,215.00",
    "low": "1,212.00",
    "qty": "32,321"
  },
  {
    "name": "Himalayan Everest Insurance Limited",
    "code": "HEI",
    "ltp": "610.00",
    "change_%": "-0.67",
    "open": "597.00",
    "high": "614.10",
    "low": "614.10",
    "qty": "10,715"
  },
  {
    "name": "Himalayan Everest Insurance Limited Promoter",
    "code": "HEIP",
    "ltp": "365.60",
    "change_%": "1.48",
    "open": "359.00",
    "high": "374.00",
    "low": "365.00",
    "qty": "15,140"
  },
  {
    "name": "Himalayan Hydropower Limited",
    "code": "HHL",
    "ltp": "499.00",
    "change_%": "-2.04",
    "open": "492.00",
    "high": "545.00",
    "low": "502.00",
    "qty": "8,656"
  },
  {
    "name": "Hydorelectricity Investment and Development Company Ltd",
    "code": "HIDCL",
    "ltp": "274.00",
    "change_%": "-1.05",
    "open": "270.00",
    "high": "280.00",
    "low": "271.40",
    "qty": "237,550"
  },
  {
    "name": "Hydroelectricity Investment and Development Company Limited Promoter Share",
    "code": "HIDCLP",
    "ltp": "178.10",
    "change_%": "-1.34",
    "open": "175.60",
    "high": "182.50",
    "low": "182.50",
    "qty": "109,767"
  },
  {
    "name": "Himalayan Laghubitta Bittiya Sanstha Limited",
    "code": "HLBSL",
    "ltp": "982.00",
    "change_%": "-0.51",
    "open": "960.10",
    "high": "1,000.00",
    "low": "1,000.00",
    "qty": "2,644"
  },
  {
    "name": "Himalayan Life Insurance Limited",
    "code": "HLI",
    "ltp": "426.50",
    "change_%": "-0.73",
    "open": "422.40",
    "high": "429.00",
    "low": "424.10",
    "qty": "29,877"
  },
  {
    "name": "Himalayan Power Partner Ltd.",
    "code": "HPPL",
    "ltp": "620.00",
    "change_%": "3.13",
    "open": "597.90",
    "high": "627.90",
    "low": "613.00",
    "qty": "296,818"
  },
  {
    "name": "Himalayan Reinsurance Limited",
    "code": "HRL",
    "ltp": "1,022.10",
    "change_%": "-1.79",
    "open": "1,010.00",
    "high": "1,053.00",
    "low": "1,040.50",
    "qty": "526,638"
  },
  {
    "name": "Himalaya Urja Bikas Company Limited",
    "code": "HURJA",
    "ltp": "244.50",
    "change_%": "-0.33",
    "open": "240.20",
    "high": "250.00",
    "low": "248.90",
    "qty": "68,739"
  },
  {
    "name": "ICFC Finance Limited",
    "code": "ICFC",
    "ltp": "608.00",
    "change_%": "-2.01",
    "open": "597.00",
    "high": "625.00",
    "low": "616.00",
    "qty": "14,302"
  },
  {
    "name": "12% ICFC Finance Limited Debenture 2083",
    "code": "ICFCD83",
    "ltp": "1,195.00",
    "change_%": "-0.42",
    "open": "1,195.00",
    "high": "1,200.00",
    "low": "1,200.00",
    "qty": "170"
  },
  {
    "name": "9% ICFC Finance Limited Debenture-2088",
    "code": "ICFCD88",
    "ltp": "1,050.10",
    "change_%": "-0.07",
    "open": "1,044.10",
    "high": "1,055.00",
    "low": "1,044.10",
    "qty": "150"
  },
  {
    "name": "IGI Prudential Insurance Company Limited",
    "code": "IGI",
    "ltp": "577.40",
    "change_%": "-1.17",
    "open": "571.00",
    "high": "582.00",
    "low": "582.00",
    "qty": "10,321"
  },
  {
    "name": "Ingwa Hydropower Limited",
    "code": "IHL",
    "ltp": "674.20",
    "change_%": "-2.46",
    "open": "670.30",
    "high": "705.00",
    "low": "705.00",
    "qty": "4,430"
  },
  {
    "name": "Infinity Laghubitta Bittiya Sanstha Limited",
    "code": "ILBS",
    "ltp": "947.00",
    "change_%": "0.83",
    "open": "918.10",
    "high": "954.00",
    "low": "954.00",
    "qty": "1,885"
  },
  {
    "name": "IME Life Insurance Company Limited",
    "code": "ILI",
    "ltp": "468.00",
    "change_%": "-0.91",
    "open": "462.00",
    "high": "472.00",
    "low": "472.00",
    "qty": "17,180"
  },
  {
    "name": "Jyoti Bikas Bank Limited",
    "code": "JBBL",
    "ltp": "341.60",
    "change_%": "-0.87",
    "open": "338.10",
    "high": "345.00",
    "low": "344.60",
    "qty": "23,963"
  },
  {
    "name": "Jeevan Bikas Laghubitta Bittiya Sanstha Limited",
    "code": "JBLB",
    "ltp": "1,341.00",
    "change_%": "-1.14",
    "open": "1,335.00",
    "high": "1,356.00",
    "low": "1,356.00",
    "qty": "1,805"
  },
  {
    "name": "Janaki Finance Ltd.",
    "code": "JFL",
    "ltp": "511.00",
    "change_%": "-1.7",
    "open": "506.20",
    "high": "524.00",
    "low": "522.60",
    "qty": "17,928"
  },
  {
    "name": "Joshi Hydropower Development Company Ltd",
    "code": "JOSHI",
    "ltp": "385.30",
    "change_%": "-2.02",
    "open": "379.30",
    "high": "403.30",
    "low": "401.00",
    "qty": "74,283"
  },
  {
    "name": "Janautthan Samudayic Laghubitta Bittiya Sanstha Limited",
    "code": "JSLBB",
    "ltp": "1,484.00",
    "change_%": "-1.86",
    "open": "1,482.00",
    "high": "1,519.00",
    "low": "1,515.00",
    "qty": "136"
  },
  {
    "name": "Kumari Bank Limited",
    "code": "KBL",
    "ltp": "207.00",
    "change_%": "-0.2",
    "open": "205.00",
    "high": "208.00",
    "low": "208.00",
    "qty": "117,019"
  },
  {
    "name": "11% KBL Debenture 2089",
    "code": "KBLD89",
    "ltp": "1,190.00",
    "change_%": "-1.65",
    "open": "1,190.00",
    "high": "1,190.00",
    "low": "1,190.00",
    "qty": "25"
  },
  {
    "name": "Kutheli Bukhari Small Hydropower Limited",
    "code": "KBSH",
    "ltp": "2,355.00",
    "change_%": "-1.36",
    "open": "2,295.00",
    "high": "2,435.00",
    "low": "2,435.00",
    "qty": "2,038"
  },
  {
    "name": "Kumari Dhanabriddhi Yojana",
    "code": "KDBY",
    "ltp": "9.19",
    "change_%": "0.33",
    "open": "8.98",
    "high": "9.19",
    "low": "8.98",
    "qty": "1,800"
  },
  {
    "name": "Kalinchowk Darshan Limited",
    "code": "KDL",
    "ltp": "1,122.70",
    "change_%": "-1.93",
    "open": "1,100.10",
    "high": "1,131.10",
    "low": "1,131.10",
    "qty": "2,874"
  },
  {
    "name": "Kumari Equity Fund",
    "code": "KEF",
    "ltp": "9.00",
    "change_%": "1.58",
    "open": "8.81",
    "high": "9.00",
    "low": "8.81",
    "qty": "12,530"
  },
  {
    "name": "Khanikhola Hydropower Co. Ltd.",
    "code": "KKHC",
    "ltp": "353.90",
    "change_%": "-0.19",
    "open": "340.10",
    "high": "361.60",
    "low": "361.60",
    "qty": "22,991"
  },
  {
    "name": "Kalika Laghubitta Bittiya Sanstha Limited",
    "code": "KMCDB",
    "ltp": "1,074.00",
    "change_%": "-0.05",
    "open": "1,054.00",
    "high": "1,090.00",
    "low": "1,087.00",
    "qty": "2,188"
  },
  {
    "name": "Kalika power Company Ltd",
    "code": "KPCL",
    "ltp": "521.00",
    "change_%": "-1.39",
    "open": "519.00",
    "high": "535.00",
    "low": "535.00",
    "qty": "8,555"
  },
  {
    "name": "Kamana Sewa Bikas Bank Limited",
    "code": "KSBBL",
    "ltp": "436.00",
    "change_%": "-0.97",
    "open": "435.50",
    "high": "441.00",
    "low": "441.00",
    "qty": "22,025"
  },
  {
    "name": "Kumari Sabal Yojana",
    "code": "KSY",
    "ltp": "9.46",
    "change_%": "3.28",
    "open": "9.30",
    "high": "9.46",
    "low": "9.30",
    "qty": "200"
  },
  {
    "name": "Lumbini Bikas Bank Ltd.",
    "code": "LBBL",
    "ltp": "421.70",
    "change_%": "-1.69",
    "open": "421.40",
    "high": "430.00",
    "low": "430.00",
    "qty": "14,536"
  },
  {
    "name": "Liberty Energy Company Limited",
    "code": "LEC",
    "ltp": "210.60",
    "change_%": "-1.85",
    "open": "209.10",
    "high": "216.00",
    "low": "210.30",
    "qty": "62,886"
  },
  {
    "name": "Life Insurance Co. Nepal",
    "code": "LICN",
    "ltp": "1,029.00",
    "change_%": "0.03",
    "open": "1,010.00",
    "high": "1,032.00",
    "low": "1,030.00",
    "qty": "16,306"
  },
  {
    "name": "Laxmi Laghubitta Bittiya Sanstha Ltd.",
    "code": "LLBS",
    "ltp": "1,060.00",
    "change_%": "-2.03",
    "open": "1,055.20",
    "high": "1,121.00",
    "low": "1,103.60",
    "qty": "570"
  },
  {
    "name": "Laxmi Sunrise Bank Limited",
    "code": "LSL",
    "ltp": "221.00",
    "change_%": "-0.95",
    "open": "219.10",
    "high": "223.00",
    "low": "219.10",
    "qty": "48,813"
  },
  {
    "name": "Laxmi unnati Kosh",
    "code": "LUK",
    "ltp": "9.89",
    "change_%": "1.54",
    "open": "9.89",
    "high": "9.89",
    "low": "9.89",
    "qty": "150"
  },
  {
    "name": "Laxmi Value Fund 2",
    "code": "LVF2",
    "ltp": "9.10",
    "change_%": "0.22",
    "open": "9.05",
    "high": "9.10",
    "low": "9.06",
    "qty": "1,100"
  },
  {
    "name": "Makar Jitumaya Suri Hydropower Limited",
    "code": "MAKAR",
    "ltp": "715.10",
    "change_%": "-1.5",
    "open": "710.00",
    "high": "747.00",
    "low": "739.00",
    "qty": "3,064"
  },
  {
    "name": "Mandu Hydropower Ltd.",
    "code": "MANDU",
    "ltp": "888.80",
    "change_%": "0.45",
    "open": "870.00",
    "high": "888.80",
    "low": "885.00",
    "qty": "1,694"
  },
  {
    "name": "Matribhumi Laghubitta Bittiya Sanstha Limited ",
    "code": "MATRI",
    "ltp": "1,215.00",
    "change_%": "-1.26",
    "open": "1,196.00",
    "high": "1,236.20",
    "low": "1,210.00",
    "qty": "1,799"
  },
  {
    "name": "Madhya Bhotekoshi Jalavidyut Company Limited",
    "code": "MBJC",
    "ltp": "322.60",
    "change_%": "-1.47",
    "open": "322.00",
    "high": "330.00",
    "low": "324.00",
    "qty": "22,787"
  },
  {
    "name": "Machhapuchchhre Bank Limited",
    "code": "MBL",
    "ltp": "227.00",
    "change_%": "-0.81",
    "open": "221.00",
    "high": "229.50",
    "low": "225.00",
    "qty": "110,868"
  },
  {
    "name": "Menchhiyam Hydropower Limited",
    "code": "MCHL",
    "ltp": "586.10",
    "change_%": "-2",
    "open": "580.20",
    "high": "609.00",
    "low": "609.00",
    "qty": "4,274"
  },
  {
    "name": "Miteri Development Bank Limited",
    "code": "MDB",
    "ltp": "635.00",
    "change_%": "-1.75",
    "open": "627.00",
    "high": "647.50",
    "low": "635.00",
    "qty": "38,562"
  },
  {
    "name": "Manakamana Engineering Hydropower Limited",
    "code": "MEHL",
    "ltp": "552.00",
    "change_%": "-1.37",
    "open": "546.00",
    "high": "580.00",
    "low": "548.50",
    "qty": "25,707"
  },
  {
    "name": "Modi Energy Limited",
    "code": "MEL",
    "ltp": "325.10",
    "change_%": "-1.89",
    "open": "320.00",
    "high": "334.90",
    "low": "331.00",
    "qty": "33,258"
  },
  {
    "name": "Mountain Energy Nepal Limited",
    "code": "MEN",
    "ltp": "583.00",
    "change_%": "-0.43",
    "open": "580.00",
    "high": "586.00",
    "low": "584.00",
    "qty": "21,770"
  },
  {
    "name": "Meromicrofinance Laghubitta Bittiya Sanstha Ltd.",
    "code": "MERO",
    "ltp": "720.00",
    "change_%": "-1.52",
    "open": "710.00",
    "high": "730.00",
    "low": "730.00",
    "qty": "4,269"
  },
  {
    "name": "Manjushree Finance Ltd.",
    "code": "MFIL",
    "ltp": "611.00",
    "change_%": "-1.06",
    "open": "605.10",
    "high": "629.80",
    "low": "629.80",
    "qty": "9,620"
  },
  {
    "name": "Molung Hydropower Company Limited",
    "code": "MHCL",
    "ltp": "515.00",
    "change_%": "-2.61",
    "open": "510.00",
    "high": "535.00",
    "low": "535.00",
    "qty": "17,399"
  },
  {
    "name": "Mandakini Hydropower Limited",
    "code": "MHL",
    "ltp": "709.10",
    "change_%": "-2.11",
    "open": "702.80",
    "high": "738.70",
    "low": "738.70",
    "qty": "2,640"
  },
  {
    "name": "Mountain Hydro Nepal Limited",
    "code": "MHNL",
    "ltp": "265.00",
    "change_%": "-2.34",
    "open": "261.00",
    "high": "274.90",
    "low": "274.90",
    "qty": "14,825"
  },
  {
    "name": "Muktinath Krishi Company Limited",
    "code": "MKCL",
    "ltp": "1,600.10",
    "change_%": "-0.85",
    "open": "1,586.00",
    "high": "1,639.00",
    "low": "1,639.00",
    "qty": "3,612"
  },
  {
    "name": "Maya Khola Hydropower Company Limited",
    "code": "MKHC",
    "ltp": "523.00",
    "change_%": "-1.84",
    "open": "512.50",
    "high": "542.00",
    "low": "522.20",
    "qty": "14,495"
  },
  {
    "name": "Mai Khola Hydropower Limited",
    "code": "MKHL",
    "ltp": "693.10",
    "change_%": "-0.44",
    "open": "683.10",
    "high": "701.00",
    "low": "696.00",
    "qty": "9,845"
  },
  {
    "name": "Mailung Khola Jal Vidhyut Company  Limited",
    "code": "MKJC",
    "ltp": "538.10",
    "change_%": "-0.46",
    "open": "532.00",
    "high": "546.00",
    "low": "535.00",
    "qty": "27,022"
  },
  {
    "name": "Mithila Laghubitta Bittiya Sanstha Ltd.",
    "code": "MLBBL",
    "ltp": "1,558.00",
    "change_%": "-0.78",
    "open": "1,521.30",
    "high": "1,575.00",
    "low": "1,540.00",
    "qty": "3,482"
  },
  {
    "name": "Mahalaxmi Bikas Bank Ltd.",
    "code": "MLBL",
    "ltp": "400.00",
    "change_%": "-1.3",
    "open": "395.00",
    "high": "408.00",
    "low": "405.00",
    "qty": "61,350"
  },
  {
    "name": "Manushi Laghubitta Bittiya Sanstha Limited",
    "code": "MLBS",
    "ltp": "1,767.00",
    "change_%": "-3.89",
    "open": "1,760.00",
    "high": "1,849.00",
    "low": "1,849.00",
    "qty": "2,161"
  },
  {
    "name": "Mahila Laghubitta Bittiya Sanstha Limited",
    "code": "MLBSL",
    "ltp": "2,224.00",
    "change_%": "-1.97",
    "open": "2,221.00",
    "high": "2,260.00",
    "low": "2,225.00",
    "qty": "1,408"
  },
  {
    "name": "Mega Mutual Fund-1",
    "code": "MMF1",
    "ltp": "8.65",
    "change_%": "1.65",
    "open": "8.34",
    "high": "8.67",
    "low": "8.34",
    "qty": "42,500"
  },
  {
    "name": "Mathillo Mailun Khola Jalvidhyut Limited",
    "code": "MMKJL",
    "ltp": "696.00",
    "change_%": "0.51",
    "open": "688.00",
    "high": "720.00",
    "low": "706.20",
    "qty": "5,509"
  },
  {
    "name": "Muktinath Bikas Bank Ltd.",
    "code": "MNBBL",
    "ltp": "367.00",
    "change_%": "-0.18",
    "open": "363.20",
    "high": "372.90",
    "low": "369.00",
    "qty": "21,457"
  },
  {
    "name": "Muktinath Mutual Fund 1",
    "code": "MNMF1",
    "ltp": "9.07",
    "change_%": "0.44",
    "open": "8.85",
    "high": "9.07",
    "low": "8.85",
    "qty": "3,460"
  },
  {
    "name": "Multipurpose Finance Company Limited",
    "code": "MPFL",
    "ltp": "641.00",
    "change_%": "-0.42",
    "open": "631.00",
    "high": "655.90",
    "low": "655.90",
    "qty": "9,399"
  },
  {
    "name": "Mid-Solu Hydropower Limited",
    "code": "MSHL",
    "ltp": "900.00",
    "change_%": "-2.08",
    "open": "887.00",
    "high": "910.00",
    "low": "901.00",
    "qty": "1,440"
  },
  {
    "name": "Mahuli Laghubitta Bittiya Sanstha Ltd.",
    "code": "MSLB",
    "ltp": "1,275.00",
    "change_%": "-2.05",
    "open": "1,265.00",
    "high": "1,290.00",
    "low": "1,285.00",
    "qty": "1,178"
  },
  {
    "name": "Narayani Development Bank Limited",
    "code": "NABBC",
    "ltp": "1,750.00",
    "change_%": "0.48",
    "open": "1,673.00",
    "high": "1,800.00",
    "low": "1,706.90",
    "qty": "60,019"
  },
  {
    "name": "Nabil Bank Limited",
    "code": "NABIL",
    "ltp": "484.60",
    "change_%": "-0.28",
    "open": "483.00",
    "high": "493.00",
    "low": "490.00",
    "qty": "28,316"
  },
  {
    "name": "9% Nabil Debenture 2087",
    "code": "NABILD87",
    "ltp": "1,073.00",
    "change_%": "0.19",
    "open": "1,073.00",
    "high": "1,073.00",
    "low": "1,073.00",
    "qty": "50"
  },
  {
    "name": "Nadep Laghubitta Bittiya Sanstha Ltd.",
    "code": "NADEP",
    "ltp": "871.00",
    "change_%": "-2.96",
    "open": "870.00",
    "high": "906.00",
    "low": "897.60",
    "qty": "1,718"
  },
  {
    "name": "NABIL BALANCED FUND-2",
    "code": "NBF2",
    "ltp": "9.50",
    "change_%": "1.06",
    "open": "9.28",
    "high": "9.50",
    "low": "9.28",
    "qty": "3,600"
  },
  {
    "name": "Nabil Balanced Fund-3",
    "code": "NBF3",
    "ltp": "9.20",
    "change_%": "1.66",
    "open": "9.01",
    "high": "9.23",
    "low": "9.23",
    "qty": "32,988"
  },
  {
    "name": "Nepal Bank Limited",
    "code": "NBL",
    "ltp": "250.00",
    "change_%": "-0.14",
    "open": "246.40",
    "high": "252.00",
    "low": "252.00",
    "qty": "62,403"
  },
  {
    "name": "10% Nabil Debenture 2082",
    "code": "NBLD82",
    "ltp": "1,078.00",
    "change_%": "0",
    "open": "1,078.00",
    "high": "1,078.00",
    "low": "1,078.00",
    "qty": "1"
  },
  {
    "name": "8.5% Nepal Bank Debenture 2087",
    "code": "NBLD87",
    "ltp": "1,026.10",
    "change_%": "-0.69",
    "open": "1,026.10",
    "high": "1,026.10",
    "low": "1,026.10",
    "qty": "25"
  },
  {
    "name": "9.5% NCC Debenture 2086",
    "code": "NCCD86",
    "ltp": "1,119.00",
    "change_%": "-1.95",
    "open": "1,119.00",
    "high": "1,119.00",
    "low": "1,119.00",
    "qty": "10"
  },
  {
    "name": "NESDO Sambridha Laghubitta Bittiye Sanstha Limited",
    "code": "NESDO",
    "ltp": "1,831.00",
    "change_%": "-1.24",
    "open": "1,818.00",
    "high": "1,868.00",
    "low": "1,818.00",
    "qty": "813"
  },
  {
    "name": "Nepal Finance Ltd.",
    "code": "NFS",
    "ltp": "699.00",
    "change_%": "-1.58",
    "open": "695.00",
    "high": "718.90",
    "low": "712.00",
    "qty": "14,887"
  },
  {
    "name": "Ngadi Group Power Ltd.",
    "code": "NGPL",
    "ltp": "272.00",
    "change_%": "-0.93",
    "open": "268.00",
    "high": "278.00",
    "low": "274.00",
    "qty": "42,280"
  },
  {
    "name": "Nepal Hydro Developers Ltd.",
    "code": "NHDL",
    "ltp": "801.00",
    "change_%": "-1.72",
    "open": "795.00",
    "high": "829.90",
    "low": "829.90",
    "qty": "3,925"
  },
  {
    "name": "National Hydro Power Company Limited",
    "code": "NHPC",
    "ltp": "209.50",
    "change_%": "-1.45",
    "open": "208.00",
    "high": "214.80",
    "low": "214.00",
    "qty": "52,102"
  },
  {
    "name": "NIBL Growth Fund",
    "code": "NIBLGF",
    "ltp": "8.42",
    "change_%": "-1.29",
    "open": "8.21",
    "high": "8.54",
    "low": "8.36",
    "qty": "5,105"
  },
  {
    "name": "NIBL Stable Fund",
    "code": "NIBLSTF",
    "ltp": "8.47",
    "change_%": "0",
    "open": "8.31",
    "high": "8.47",
    "low": "8.31",
    "qty": "7,177"
  },
  {
    "name": "NIBL Samriddhi Fund 2",
    "code": "NIBSF2",
    "ltp": "8.22",
    "change_%": "-1.67",
    "open": "8.21",
    "high": "8.50",
    "low": "8.21",
    "qty": "17,803"
  },
  {
    "name": "NIC Asia Bank Ltd.",
    "code": "NICA",
    "ltp": "371.20",
    "change_%": "-1.39",
    "open": "369.00",
    "high": "379.00",
    "low": "375.00",
    "qty": "26,641"
  },
  {
    "name": "NIC Asia Debenture 2085/86",
    "code": "NICAD85/86",
    "ltp": "1,100.00",
    "change_%": "-0.9",
    "open": "1,100.00",
    "high": "1,100.00",
    "low": "1,100.00",
    "qty": "50"
  },
  {
    "name": "NIC Asia Balanced Fund",
    "code": "NICBF",
    "ltp": "9.27",
    "change_%": "1.98",
    "open": "9.20",
    "high": "9.27",
    "low": "9.20",
    "qty": "2,000"
  },
  {
    "name": "8.5% NIC Asia Rinpatra 2088",
    "code": "NICD88",
    "ltp": "1,030.10",
    "change_%": "-1.66",
    "open": "1,030.10",
    "high": "1,030.10",
    "low": "1,030.10",
    "qty": "25"
  },
  {
    "name": "NIC ASIA Flexi CAP Fund",
    "code": "NICFC",
    "ltp": "8.98",
    "change_%": "-0.22",
    "open": "8.80",
    "high": "8.98",
    "low": "8.85",
    "qty": "1,200"
  },
  {
    "name": "NIC Asia Growth Fund-2",
    "code": "NICGF2",
    "ltp": "8.56",
    "change_%": "-0.47",
    "open": "8.56",
    "high": "8.60",
    "low": "8.60",
    "qty": "820"
  },
  {
    "name": "Nepal Insurance Co. Ltd.",
    "code": "NICL",
    "ltp": "835.80",
    "change_%": "0.2",
    "open": "830.00",
    "high": "848.00",
    "low": "848.00",
    "qty": "2,811"
  },
  {
    "name": "NIC Asia Laghubitta Biitiya Sanstha Limited",
    "code": "NICLBSL",
    "ltp": "652.00",
    "change_%": "-1.49",
    "open": "648.90",
    "high": "673.00",
    "low": "660.00",
    "qty": "5,448"
  },
  {
    "name": "NIC Asia Select - 30 (Index Fund",
    "code": "NICSF",
    "ltp": "8.95",
    "change_%": "-0.33",
    "open": "8.83",
    "high": "9.14",
    "low": "8.83",
    "qty": "5,050"
  },
  {
    "name": "Nepal Infrastructure Bank Limited",
    "code": "NIFRA",
    "ltp": "273.60",
    "change_%": "-1.49",
    "open": "268.20",
    "high": "278.00",
    "low": "275.00",
    "qty": "165,649"
  },
  {
    "name": "Neco Insurance Co. Ltd.",
    "code": "NIL",
    "ltp": "753.00",
    "change_%": "-0.52",
    "open": "745.60",
    "high": "756.00",
    "low": "753.00",
    "qty": "3,624"
  },
  {
    "name": "Nepal Investment Mega Bank Limited ",
    "code": "NIMB",
    "ltp": "212.10",
    "change_%": "-0.69",
    "open": "210.20",
    "high": "216.80",
    "low": "216.80",
    "qty": "51,549"
  },
  {
    "name": "10% NIMB Debenture 2090",
    "code": "NIMBD90",
    "ltp": "1,121.00",
    "change_%": "-0.36",
    "open": "1,121.00",
    "high": "1,121.00",
    "low": "1,121.00",
    "qty": "25"
  },
  {
    "name": "Nepal Investment Mega Bank Ltd. Promoter Share ",
    "code": "NIMBPO",
    "ltp": "157.40",
    "change_%": "0.9",
    "open": "152.90",
    "high": "157.40",
    "low": "152.90",
    "qty": "118"
  },
  {
    "name": "NLG Insurance Company Ltd.",
    "code": "NLG",
    "ltp": "859.60",
    "change_%": "-1.59",
    "open": "855.00",
    "high": "884.00",
    "low": "873.00",
    "qty": "26,492"
  },
  {
    "name": "Nepal Life Insurance Co. Ltd.",
    "code": "NLIC",
    "ltp": "781.30",
    "change_%": "-1.13",
    "open": "774.50",
    "high": "799.50",
    "low": "774.50",
    "qty": "22,813"
  },
  {
    "name": "National Life Insurance Co. Ltd.",
    "code": "NLICL",
    "ltp": "648.00",
    "change_%": "-0.22",
    "open": "636.50",
    "high": "662.30",
    "low": "653.00",
    "qty": "76,308"
  },
  {
    "name": "NMB Bank Limited",
    "code": "NMB",
    "ltp": "254.80",
    "change_%": "-0.95",
    "open": "253.20",
    "high": "258.00",
    "low": "258.00",
    "qty": "36,400"
  },
  {
    "name": "NMB 50",
    "code": "NMB50",
    "ltp": "10.41",
    "change_%": "0",
    "open": "10.41",
    "high": "10.41",
    "low": "10.41",
    "qty": "100"
  },
  {
    "name": "NMB Debenture 10.75%-2089/2090",
    "code": "NMBD89/90",
    "ltp": "1,145.10",
    "change_%": "-2.96",
    "open": "1,145.10",
    "high": "1,156.40",
    "low": "1,156.40",
    "qty": "190"
  },
  {
    "name": "NMB Laghubitta Bittiya Sanstha Ltd.",
    "code": "NMBMF",
    "ltp": "727.10",
    "change_%": "-2.89",
    "open": "727.10",
    "high": "763.70",
    "low": "763.70",
    "qty": "1,943"
  },
  {
    "name": "National Laghubitta Bittiya Sanstha Limited",
    "code": "NMFBS",
    "ltp": "1,220.00",
    "change_%": "-1.5",
    "open": "1,214.40",
    "high": "1,222.00",
    "low": "1,220.30",
    "qty": "1,535"
  },
  {
    "name": "Nerude Mirmire Laghubitta Bittiya Sanstha Limited",
    "code": "NMLBBL",
    "ltp": "660.00",
    "change_%": "-1.53",
    "open": "658.20",
    "high": "680.00",
    "low": "680.00",
    "qty": "2,220"
  },
  {
    "name": "Nepal Re-Insurance Company Limited",
    "code": "NRIC",
    "ltp": "1,312.10",
    "change_%": "-2.27",
    "open": "1,303.00",
    "high": "1,354.00",
    "low": "1,342.60",
    "qty": "175,313"
  },
  {
    "name": "Nepal Republic Media Limited",
    "code": "NRM",
    "ltp": "496.00",
    "change_%": "-2.29",
    "open": "490.00",
    "high": "513.90",
    "low": "497.50",
    "qty": "59,584"
  },
  {
    "name": "NRN Infrastructure and Development Limited",
    "code": "NRN",
    "ltp": "1,588.00",
    "change_%": "2.02",
    "open": "1,541.10",
    "high": "1,614.00",
    "low": "1,557.00",
    "qty": "220,827"
  },
  {
    "name": "NMB Sulav Investment Fund - 2",
    "code": "NSIF2",
    "ltp": "10.22",
    "change_%": "-0.2",
    "open": "10.10",
    "high": "10.23",
    "low": "10.10",
    "qty": "1,250"
  },
  {
    "name": "Nepal Doorsanchar Comapany Limited",
    "code": "NTC",
    "ltp": "904.00",
    "change_%": "-0.03",
    "open": "900.00",
    "high": "909.80",
    "low": "903.00",
    "qty": "6,207"
  },
  {
    "name": "Nirdhan Utthan Laghubitta Bittiya Sanstha Limited",
    "code": "NUBL",
    "ltp": "684.00",
    "change_%": "-1.13",
    "open": "665.10",
    "high": "699.00",
    "low": "692.00",
    "qty": "12,767"
  },
  {
    "name": "Nepal Warehousing Company Limited",
    "code": "NWCL",
    "ltp": "950.00",
    "change_%": "-2.93",
    "open": "945.00",
    "high": "990.00",
    "low": "990.00",
    "qty": "3,968"
  },
  {
    "name": "Nyadi Hydropower Limited",
    "code": "NYADI",
    "ltp": "602.00",
    "change_%": "0.94",
    "open": "591.60",
    "high": "608.00",
    "low": "600.00",
    "qty": "49,762"
  },
  {
    "name": "Oriental Hotels Limited",
    "code": "OHL",
    "ltp": "877.70",
    "change_%": "-2.42",
    "open": "877.70",
    "high": "910.00",
    "low": "910.00",
    "qty": "3,386"
  },
  {
    "name": "10% Prime Debenture 2088",
    "code": "PBD88",
    "ltp": "1,122.00",
    "change_%": "-1.92",
    "open": "1,122.00",
    "high": "1,122.00",
    "low": "1,122.00",
    "qty": "50"
  },
  {
    "name": "Prime Commercial Bank Ltd.",
    "code": "PCBL",
    "ltp": "253.50",
    "change_%": "0.09",
    "open": "250.00",
    "high": "253.50",
    "low": "253.50",
    "qty": "68,325"
  },
  {
    "name": "Pokhara Finance Ltd.",
    "code": "PFL",
    "ltp": "432.00",
    "change_%": "-1.89",
    "open": "426.40",
    "high": "443.00",
    "low": "440.00",
    "qty": "21,037"
  },
  {
    "name": "Peoples Hydropower Company Limited",
    "code": "PHCL",
    "ltp": "580.00",
    "change_%": "-0.13",
    "open": "573.30",
    "high": "590.00",
    "low": "580.00",
    "qty": "31,736"
  },
  {
    "name": "Panchakanya Mai Hydropower Ltd",
    "code": "PMHPL",
    "ltp": "294.00",
    "change_%": "-1.65",
    "open": "290.30",
    "high": "299.80",
    "low": "295.00",
    "qty": "7,848"
  },
  {
    "name": "Prabhu Mahalaxmi Life Insurance Limited",
    "code": "PMLI",
    "ltp": "565.00",
    "change_%": "-1.25",
    "open": "560.30",
    "high": "580.10",
    "low": "580.10",
    "qty": "7,412"
  },
  {
    "name": "Panchthar Power Company Limited",
    "code": "PPCL",
    "ltp": "318.00",
    "change_%": "0.32",
    "open": "315.00",
    "high": "322.90",
    "low": "322.90",
    "qty": "23,784"
  },
  {
    "name": "Peopl",
    "code": "PPL",
    "ltp": "522.50",
    "change_%": "-3.89",
    "open": "519.90",
    "high": "543.40",
    "low": "532.80",
    "qty": "13,851"
  },
  {
    "name": "Prabhu Insurance Ltd.",
    "code": "PRIN",
    "ltp": "930.00",
    "change_%": "-0.38",
    "open": "920.00",
    "high": "957.00",
    "low": "951.00",
    "qty": "13,138"
  },
  {
    "name": "Progressive Finance Limited",
    "code": "PROFL",
    "ltp": "550.00",
    "change_%": "-1.56",
    "open": "543.00",
    "high": "565.00",
    "low": "564.00",
    "qty": "20,831"
  },
  {
    "name": "Progressive Finance Limited Promoter Share",
    "code": "PROFLP",
    "ltp": "118.00",
    "change_%": "0",
    "open": "118.00",
    "high": "118.00",
    "low": "118.00",
    "qty": "100"
  },
  {
    "name": "Prabhu Smart Fund",
    "code": "PRSF",
    "ltp": "10.14",
    "change_%": "-2.69",
    "open": "10.11",
    "high": "10.35",
    "low": "10.22",
    "qty": "278,500"
  },
  {
    "name": "Prabhu Bank Limited",
    "code": "PRVU",
    "ltp": "212.60",
    "change_%": "-1.11",
    "open": "210.10",
    "high": "215.80",
    "low": "215.00",
    "qty": "123,582"
  },
  {
    "name": "Prabhu Select Fund",
    "code": "PSF",
    "ltp": "10.20",
    "change_%": "0.49",
    "open": "10.15",
    "high": "10.20",
    "low": "10.15",
    "qty": "9,500"
  },
  {
    "name": "Radhi Bidyut Company Ltd",
    "code": "RADHI",
    "ltp": "395.00",
    "change_%": "1.15",
    "open": "388.10",
    "high": "397.80",
    "low": "391.00",
    "qty": "66,404"
  },
  {
    "name": "Rawa Energy Development Limited",
    "code": "RAWA",
    "ltp": "881.00",
    "change_%": "1.11",
    "open": "851.00",
    "high": "888.00",
    "low": "860.50",
    "qty": "9,240"
  },
  {
    "name": "Rastriya Beema Company Limited",
    "code": "RBCL",
    "ltp": "14,800.00",
    "change_%": "-0.12",
    "open": "14,800.00",
    "high": "14,800.00",
    "low": "14,800.00",
    "qty": "10"
  },
  {
    "name": "Rastriya Beema Company Limited Promoter Share",
    "code": "RBCLPO",
    "ltp": "11,352.00",
    "change_%": "-1.64",
    "open": "11,352.00",
    "high": "11,550.00",
    "low": "11,550.00",
    "qty": "130"
  },
  {
    "name": "River Falls Power Limited",
    "code": "RFPL",
    "ltp": "691.00",
    "change_%": "-2.29",
    "open": "687.00",
    "high": "719.00",
    "low": "713.00",
    "qty": "5,379"
  },
  {
    "name": "Rapti Hydro and General Construction Limited",
    "code": "RHGCL",
    "ltp": "542.10",
    "change_%": "-1.51",
    "open": "540.00",
    "high": "581.00",
    "low": "540.00",
    "qty": "6,432"
  },
  {
    "name": "RASUWAGADHI HYDROPOWER COMPANY LIMITED",
    "code": "RHPL",
    "ltp": "381.00",
    "change_%": "-1.58",
    "open": "376.50",
    "high": "390.00",
    "low": "380.10",
    "qty": "27,966"
  },
  {
    "name": "Ridi Power Company Limited",
    "code": "RIDI",
    "ltp": "223.00",
    "change_%": "-1.4",
    "open": "220.00",
    "high": "230.60",
    "low": "230.60",
    "qty": "40,146"
  },
  {
    "name": "Reliance Finance Ltd.",
    "code": "RLFL",
    "ltp": "535.00",
    "change_%": "-2.17",
    "open": "527.50",
    "high": "546.80",
    "low": "545.90",
    "qty": "23,418"
  },
  {
    "name": "RBB Mutual Fund 1",
    "code": "RMF1",
    "ltp": "8.83",
    "change_%": "-1.89",
    "open": "8.83",
    "high": "9.07",
    "low": "9.07",
    "qty": "90,600"
  },
  {
    "name": "RBB Mutual Fund 2",
    "code": "RMF2",
    "ltp": "8.97",
    "change_%": "-3.86",
    "open": "8.97",
    "high": "9.33",
    "low": "9.15",
    "qty": "882"
  },
  {
    "name": "Reliable Nepal Life Insurance Limited",
    "code": "RNLI",
    "ltp": "549.00",
    "change_%": "-0.58",
    "open": "540.00",
    "high": "553.50",
    "low": "553.00",
    "qty": "62,962"
  },
  {
    "name": "RSDC Laghubitta Bittiya Sanstha Ltd.",
    "code": "RSDC",
    "ltp": "717.00",
    "change_%": "-0.01",
    "open": "711.00",
    "high": "725.00",
    "low": "720.00",
    "qty": "22,256"
  },
  {
    "name": "Ru Ru Jalbidhyut Pariyojana Limited",
    "code": "RURU",
    "ltp": "730.00",
    "change_%": "-1.34",
    "open": "720.00",
    "high": "750.00",
    "low": "750.00",
    "qty": "17,989"
  },
  {
    "name": "Shangrila Development Bank Ltd.",
    "code": "SADBL",
    "ltp": "406.00",
    "change_%": "-1.54",
    "open": "403.40",
    "high": "414.00",
    "low": "408.00",
    "qty": "23,505"
  },
  {
    "name": "Sanima Growth Fund",
    "code": "SAGF",
    "ltp": "9.34",
    "change_%": "0.43",
    "open": "9.12",
    "high": "9.40",
    "low": "9.40",
    "qty": "253,400"
  },
  {
    "name": "Sahas Urja Limited",
    "code": "SAHAS",
    "ltp": "502.00",
    "change_%": "-0.13",
    "open": "498.00",
    "high": "509.80",
    "low": "509.40",
    "qty": "43,445"
  },
  {
    "name": "Sagarmatha Lumbini Insurance Co. Limited",
    "code": "SALICO",
    "ltp": "712.00",
    "change_%": "-0.85",
    "open": "708.00",
    "high": "715.10",
    "low": "715.00",
    "qty": "4,520"
  },
  {
    "name": "Samaj Laghubittya Bittiya Sanstha Limited",
    "code": "SAMAJ",
    "ltp": "2,610.00",
    "change_%": "0.1",
    "open": "2,555.00",
    "high": "2,615.00",
    "low": "2,563.00",
    "qty": "326"
  },
  {
    "name": "Sanima Bank Limited",
    "code": "SANIMA",
    "ltp": "300.00",
    "change_%": "-0.7",
    "open": "298.00",
    "high": "306.00",
    "low": "300.00",
    "qty": "43,567"
  },
  {
    "name": "Saptakoshi Development Bank Ltd",
    "code": "SAPDBL",
    "ltp": "1,087.00",
    "change_%": "-0.92",
    "open": "1,077.10",
    "high": "1,113.00",
    "low": "1,077.10",
    "qty": "20,382"
  },
  {
    "name": "Sarbottam Cement Limited",
    "code": "SARBTM",
    "ltp": "807.00",
    "change_%": "-0.41",
    "open": "795.10",
    "high": "825.00",
    "low": "825.00",
    "qty": "26,113"
  },
  {
    "name": "Sunrise Bluechip Fund",
    "code": "SBCF",
    "ltp": "8.95",
    "change_%": "-1.21",
    "open": "8.93",
    "high": "9.00",
    "low": "8.99",
    "qty": "4,200"
  },
  {
    "name": "Nepal SBI Bank Limited",
    "code": "SBI",
    "ltp": "412.10",
    "change_%": "-1.15",
    "open": "410.20",
    "high": "418.50",
    "low": "413.00",
    "qty": "12,186"
  },
  {
    "name": "9% Nepal SBI Bank debenture 2089",
    "code": "SBID89",
    "ltp": "1,050.10",
    "change_%": "-0.01",
    "open": "1,050.00",
    "high": "1,050.10",
    "low": "1,050.00",
    "qty": "40"
  },
  {
    "name": "Siddhartha Bank Limited",
    "code": "SBL",
    "ltp": "288.30",
    "change_%": "-1.51",
    "open": "286.90",
    "high": "292.50",
    "low": "286.90",
    "qty": "20,083"
  },
  {
    "name": "Standard Chartered Bank Limited",
    "code": "SCB",
    "ltp": "630.00",
    "change_%": "-0.69",
    "open": "629.10",
    "high": "636.00",
    "low": "635.00",
    "qty": "11,301"
  },
  {
    "name": "Siddhartha Equity Fund",
    "code": "SEF",
    "ltp": "9.82",
    "change_%": "-0.61",
    "open": "9.81",
    "high": "10.00",
    "low": "10.00",
    "qty": "2,500"
  },
  {
    "name": "Samriddhi Finance Company Limited",
    "code": "SFCL",
    "ltp": "541.50",
    "change_%": "-3.48",
    "open": "538.00",
    "high": "568.00",
    "low": "555.00",
    "qty": "28,780"
  },
  {
    "name": "Sunrise Focused Equity Fund",
    "code": "SFEF",
    "ltp": "9.06",
    "change_%": "-0.55",
    "open": "8.95",
    "high": "9.24",
    "low": "8.95",
    "qty": "1,200"
  },
  {
    "name": "Swet-Ganga Hydropower & Construction Limited ",
    "code": "SGHC",
    "ltp": "536.00",
    "change_%": "-0.78",
    "open": "525.00",
    "high": "538.50",
    "low": "533.00",
    "qty": "24,867"
  },
  {
    "name": "Sanima GIC Insurance Limited",
    "code": "SGIC",
    "ltp": "591.60",
    "change_%": "-1.31",
    "open": "584.00",
    "high": "600.10",
    "low": "595.10",
    "qty": "18,617"
  },
  {
    "name": "Singati Hydro Energy Limited",
    "code": "SHEL",
    "ltp": "253.00",
    "change_%": "-1.78",
    "open": "249.10",
    "high": "258.00",
    "low": "255.70",
    "qty": "80,333"
  },
  {
    "name": "Shine Resunga Development Bank Ltd.",
    "code": "SHINE",
    "ltp": "411.50",
    "change_%": "-1.47",
    "open": "411.00",
    "high": "419.00",
    "low": "419.00",
    "qty": "18,728"
  },
  {
    "name": "SHIVAM CEMENTS LTD",
    "code": "SHIVM",
    "ltp": "533.70",
    "change_%": "-1.31",
    "open": "530.20",
    "high": "543.00",
    "low": "535.00",
    "qty": "38,401"
  },
  {
    "name": "Soaltee Hotel Limited",
    "code": "SHL",
    "ltp": "480.00",
    "change_%": "-1.33",
    "open": "470.00",
    "high": "486.00",
    "low": "480.00",
    "qty": "20,804"
  },
  {
    "name": "Shrijanshil Laghubitta Bittiya Sanstha Limited",
    "code": "SHLB",
    "ltp": "2,286.00",
    "change_%": "0.68",
    "open": "2,190.00",
    "high": "2,286.00",
    "low": "2,241.00",
    "qty": "1,904"
  },
  {
    "name": "Sanima Mai Hydropower Ltd.",
    "code": "SHPC",
    "ltp": "470.20",
    "change_%": "-2.02",
    "open": "467.00",
    "high": "480.00",
    "low": "480.00",
    "qty": "38,884"
  },
  {
    "name": "Shikhar Insurance Co. Ltd.",
    "code": "SICL",
    "ltp": "783.00",
    "change_%": "-0.2",
    "open": "776.00",
    "high": "795.00",
    "low": "795.00",
    "qty": "6,498"
  },
  {
    "name": "Shree Investment Finance Co. Ltd.",
    "code": "SIFC",
    "ltp": "533.00",
    "change_%": "-1.61",
    "open": "522.20",
    "high": "550.00",
    "low": "550.00",
    "qty": "5,497"
  },
  {
    "name": "Siddhartha Investment Growth Scheme - 2",
    "code": "SIGS2",
    "ltp": "9.70",
    "change_%": "1.04",
    "open": "9.43",
    "high": "9.78",
    "low": "9.44",
    "qty": "16,125"
  },
  {
    "name": "Siddhartha Investment Growth Scheme 3\t",
    "code": "SIGS3",
    "ltp": "9.90",
    "change_%": "1.02",
    "open": "9.71",
    "high": "9.90",
    "low": "9.71",
    "qty": "1,900"
  },
  {
    "name": "Sikles Hydropower Limited",
    "code": "SIKLES",
    "ltp": "1,160.00",
    "change_%": "-1.29",
    "open": "1,133.00",
    "high": "1,162.00",
    "low": "1,154.00",
    "qty": "1,887"
  },
  {
    "name": "Sindhu Bikash Bank Ltd",
    "code": "SINDU",
    "ltp": "1,149.00",
    "change_%": "2.02",
    "open": "1,110.00",
    "high": "1,168.10",
    "low": "1,110.00",
    "qty": "78,366"
  },
  {
    "name": "SANJEN JALAVIDHYUT COMPANY LIMITED",
    "code": "SJCL",
    "ltp": "316.00",
    "change_%": "-3.79",
    "open": "310.00",
    "high": "330.00",
    "low": "325.20",
    "qty": "44,970"
  },
  {
    "name": "SuryaJyoti Life Insurance Company Limited",
    "code": "SJLIC",
    "ltp": "445.00",
    "change_%": "-0.49",
    "open": "441.00",
    "high": "449.90",
    "low": "441.00",
    "qty": "21,313"
  },
  {
    "name": "Sana Kisan Bikas Laghubitta Bittiya sanstha Limited.",
    "code": "SKBBL",
    "ltp": "804.60",
    "change_%": "0.79",
    "open": "798.00",
    "high": "811.00",
    "low": "811.00",
    "qty": "16,270"
  },
  {
    "name": "Swarojgar Laghubitta Bittiya Sanstha Ltd.",
    "code": "SLBBL",
    "ltp": "970.00",
    "change_%": "-1.53",
    "open": "966.00",
    "high": "987.00",
    "low": "967.10",
    "qty": "8,851"
  },
  {
    "name": "Samudayik Laghubitta Bittiya Sanstha Limited",
    "code": "SLBSL",
    "ltp": "2,000.00",
    "change_%": "-1.91",
    "open": "1,980.30",
    "high": "2,079.80",
    "low": "2,079.80",
    "qty": "1,491"
  },
  {
    "name": "Sanima Large Cap Fund",
    "code": "SLCF",
    "ltp": "9.35",
    "change_%": "-0.21",
    "open": "9.33",
    "high": "9.50",
    "low": "9.50",
    "qty": "2,100"
  },
  {
    "name": "Samata Gharelu Laghubitta Bittiya Sanstha Limited",
    "code": "SMATA",
    "ltp": "814.10",
    "change_%": "-2.15",
    "open": "810.70",
    "high": "824.00",
    "low": "820.00",
    "qty": "2,482"
  },
  {
    "name": "Support Microfinance Bittiya Sanstha Ltd.",
    "code": "SMB",
    "ltp": "2,498.50",
    "change_%": "-2.25",
    "open": "2,420.00",
    "high": "2,580.00",
    "low": "2,570.00",
    "qty": "3,080"
  },
  {
    "name": "Swabhimaan Laghubitta Bittiya Sanstha Ltd",
    "code": "SMFBS",
    "ltp": "1,875.00",
    "change_%": "-2.35",
    "open": "1,860.20",
    "high": "1,948.00",
    "low": "1,948.00",
    "qty": "257"
  },
  {
    "name": "Super Mai Hydropower Limited",
    "code": "SMH",
    "ltp": "922.00",
    "change_%": "-1.46",
    "open": "918.00",
    "high": "936.00",
    "low": "918.00",
    "qty": "2,282"
  },
  {
    "name": "Super Madi Hydropower Limited",
    "code": "SMHL",
    "ltp": "877.10",
    "change_%": "-0.98",
    "open": "871.00",
    "high": "900.00",
    "low": "900.00",
    "qty": "2,131"
  },
  {
    "name": "Sagarmatha Jalabidhyut Company Limited",
    "code": "SMJC",
    "ltp": "585.00",
    "change_%": "-1.27",
    "open": "580.10",
    "high": "604.30",
    "low": "604.30",
    "qty": "20,819"
  },
  {
    "name": "Sampada Laghubitta Bittiya Sanstha Limited",
    "code": "SMPDA",
    "ltp": "941.00",
    "change_%": "-1.62",
    "open": "918.70",
    "high": "994.00",
    "low": "945.00",
    "qty": "5,301"
  },
  {
    "name": "Sun Nepal Life Insurance Company Limited",
    "code": "SNLI",
    "ltp": "645.10",
    "change_%": "-1.39",
    "open": "640.00",
    "high": "660.00",
    "low": "654.00",
    "qty": "18,104"
  },
  {
    "name": "Sonapur Minerals and Oil Limited",
    "code": "SONA",
    "ltp": "473.40",
    "change_%": "-1.3",
    "open": "467.00",
    "high": "480.00",
    "low": "480.00",
    "qty": "51,420"
  },
  {
    "name": "Samling Power Company Limited",
    "code": "SPC",
    "ltp": "540.00",
    "change_%": "-2.6",
    "open": "535.00",
    "high": "560.00",
    "low": "555.00",
    "qty": "28,754"
  },
  {
    "name": "Synergy Power Development Ltd.",
    "code": "SPDL",
    "ltp": "322.00",
    "change_%": "-1.05",
    "open": "320.10",
    "high": "328.00",
    "low": "327.00",
    "qty": "33,025"
  },
  {
    "name": "Sayapatri Hydropower Limited",
    "code": "SPHL",
    "ltp": "758.00",
    "change_%": "-1.26",
    "open": "752.40",
    "high": "767.40",
    "low": "752.40",
    "qty": "740"
  },
  {
    "name": "Siddhartha Premier Insurance Limited",
    "code": "SPIL",
    "ltp": "820.50",
    "change_%": "-0.71",
    "open": "815.00",
    "high": "842.80",
    "low": "842.00",
    "qty": "4,020"
  },
  {
    "name": "Shuvam Power Company Limited",
    "code": "SPL",
    "ltp": "880.00",
    "change_%": "-0.56",
    "open": "868.10",
    "high": "881.00",
    "low": "881.00",
    "qty": "1,170"
  },
  {
    "name": "Sanima Reliance Life Insurance Limited",
    "code": "SRLI",
    "ltp": "418.00",
    "change_%": "-0.91",
    "open": "416.00",
    "high": "428.00",
    "low": "421.00",
    "qty": "23,002"
  },
  {
    "name": "Shiva Shree Hydropower Limited",
    "code": "SSHL",
    "ltp": "232.00",
    "change_%": "-0.77",
    "open": "228.00",
    "high": "235.90",
    "low": "235.00",
    "qty": "56,835"
  },
  {
    "name": "Salt Trading Corporation",
    "code": "STC",
    "ltp": "5,219.00",
    "change_%": "0.71",
    "open": "5,151.10",
    "high": "5,286.00",
    "low": "5,286.00",
    "qty": "451"
  },
  {
    "name": "Swabalamban Laghubitta Bittiya Sanstha Limited",
    "code": "SWBBL",
    "ltp": "825.00",
    "change_%": "-1.02",
    "open": "813.50",
    "high": "840.00",
    "low": "840.00",
    "qty": "7,443"
  },
  {
    "name": "Suryodaya Womi Laghubitta Bittiya Sanstha Limited ",
    "code": "SWMF",
    "ltp": "741.00",
    "change_%": "-0.55",
    "open": "737.00",
    "high": "758.00",
    "low": "737.00",
    "qty": "2,966"
  },
  {
    "name": "Sanima Middle Tamor Hydropower Limited",
    "code": "TAMOR",
    "ltp": "520.00",
    "change_%": "-0.46",
    "open": "513.10",
    "high": "524.00",
    "low": "522.00",
    "qty": "20,672"
  },
  {
    "name": "Terhathum Power Company Limited",
    "code": "TPC",
    "ltp": "540.00",
    "change_%": "-0.89",
    "open": "529.10",
    "high": "545.00",
    "low": "538.10",
    "qty": "14,901"
  },
  {
    "name": "Taragaon Regency Hotel Limited",
    "code": "TRH",
    "ltp": "1,050.00",
    "change_%": "-1.79",
    "open": "1,050.00",
    "high": "1,056.00",
    "low": "1,056.00",
    "qty": "1,106"
  },
  {
    "name": "Three Star Hydropower Limited",
    "code": "TSHL",
    "ltp": "808.00",
    "change_%": "0.36",
    "open": "791.00",
    "high": "816.00",
    "low": "791.00",
    "qty": "1,931"
  },
  {
    "name": "Trishuli Jal Vidhyut Company Limited",
    "code": "TVCL",
    "ltp": "529.00",
    "change_%": "-1.67",
    "open": "520.00",
    "high": "540.00",
    "low": "530.10",
    "qty": "11,776"
  },
  {
    "name": "United Ajod Insurance Limited ",
    "code": "UAIL",
    "ltp": "641.10",
    "change_%": "-0.42",
    "open": "638.00",
    "high": "643.90",
    "low": "643.00",
    "qty": "13,384"
  },
  {
    "name": "Upper Hewakhola Hydropower Company Limited",
    "code": "UHEWA",
    "ltp": "750.00",
    "change_%": "-2.01",
    "open": "748.10",
    "high": "779.90",
    "low": "765.00",
    "qty": "15,389"
  },
  {
    "name": "Upakar Laghubitta Bittiya Sanstha Limited",
    "code": "ULBSL",
    "ltp": "3,357.00",
    "change_%": "-1.73",
    "open": "3,293.00",
    "high": "3,414.00",
    "low": "3,347.90",
    "qty": "1,736"
  },
  {
    "name": "Upper Lohore Khola Hydropower Company Limited",
    "code": "ULHC",
    "ltp": "521.00",
    "change_%": "-1.85",
    "open": "516.30",
    "high": "541.00",
    "low": "541.00",
    "qty": "22,209"
  },
  {
    "name": "United Modi Hydropower Ltd.",
    "code": "UMHL",
    "ltp": "445.10",
    "change_%": "1.64",
    "open": "434.00",
    "high": "450.00",
    "low": "435.10",
    "qty": "285,126"
  },
  {
    "name": "United IDI Mardi RB Hydropower Limited.",
    "code": "UMRH",
    "ltp": "609.00",
    "change_%": "-1.79",
    "open": "605.20",
    "high": "632.00",
    "low": "632.00",
    "qty": "18,634"
  },
  {
    "name": "Union Hydropower Limited",
    "code": "UNHPL",
    "ltp": "315.00",
    "change_%": "-0.76",
    "open": "309.00",
    "high": "320.00",
    "low": "316.50",
    "qty": "35,240"
  },
  {
    "name": "Unilever Nepal Limited",
    "code": "UNL",
    "ltp": "47,480.00",
    "change_%": "3.21",
    "open": "46,000.00",
    "high": "47,480.00",
    "low": "46,000.00",
    "qty": "40"
  },
  {
    "name": "Unique Nepal Laghubitta Bittiya Sanstha Limited",
    "code": "UNLB",
    "ltp": "2,255.00",
    "change_%": "-2.15",
    "open": "2,209.90",
    "high": "2,280.00",
    "low": "2,280.00",
    "qty": "939"
  },
  {
    "name": "Unique Nepal Laghubitta Bittiya Sanstha Limited Promoter",
    "code": "UNLBP",
    "ltp": "1,211.00",
    "change_%": "0",
    "open": "1,211.00",
    "high": "1,211.00",
    "low": "1,211.00",
    "qty": "3,000"
  },
  {
    "name": "UNIVERSAL POWER COMPANY LTD",
    "code": "UPCL",
    "ltp": "287.20",
    "change_%": "-1.68",
    "open": "286.00",
    "high": "296.90",
    "low": "292.10",
    "qty": "84,670"
  },
  {
    "name": "Upper Tamakoshi Hydropower Ltd",
    "code": "UPPER",
    "ltp": "201.40",
    "change_%": "-0.55",
    "open": "200.80",
    "high": "204.00",
    "low": "202.80",
    "qty": "78,187"
  },
  {
    "name": "Upper Solu Hydro Electric Company Limited ",
    "code": "USHEC",
    "ltp": "603.00",
    "change_%": "-1.51",
    "open": "594.00",
    "high": "623.90",
    "low": "605.00",
    "qty": "4,475"
  },
  {
    "name": "Upper Syange  Hydropower Limited",
    "code": "USHL",
    "ltp": "748.00",
    "change_%": "0.18",
    "open": "734.10",
    "high": "750.00",
    "low": "750.00",
    "qty": "1,856"
  },
  {
    "name": "Unnati Sahakarya Laghubitta Bittiya Sanstha Limited",
    "code": "USLB",
    "ltp": "1,660.00",
    "change_%": "-1.21",
    "open": "1,649.00",
    "high": "1,686.00",
    "low": "1,685.10",
    "qty": "2,935"
  },
  {
    "name": "Vijaya laghubitta Bittiya Sanstha Ltd.",
    "code": "VLBS",
    "ltp": "855.00",
    "change_%": "-1.15",
    "open": "841.20",
    "high": "870.00",
    "low": "870.00",
    "qty": "1,495"
  },
  {
    "name": "Vision Lumbini Urja Company Limited",
    "code": "VLUCL",
    "ltp": "668.00",
    "change_%": "-2.79",
    "open": "660.80",
    "high": "699.00",
    "low": "674.20",
    "qty": "11,944"
  },
  {
    "name": "WEAN Nepal Laghubitta Bittiya Sanstha Limited",
    "code": "WNLB",
    "ltp": "3,050.00",
    "change_%": "-0.92",
    "open": "2,905.00",
    "high": "3,054.00",
    "low": "3,054.00",
    "qty": "1,418"
  }
]